jsonllm/__init__.py
jsonllm/cli.py
jsonllm-0.0.1.dist-info/LICENSE
jsonllm-0.0.1.dist-info/METADATA
jsonllm-0.0.1.dist-info/WHEEL
jsonllm-0.0.1.dist-info/entry_points.txt
jsonllm-0.0.1.dist-info/top_level.txt
jsonllm-0.0.1.dist-info/RECORD
