Metadata-Version: 2.1
Name: jsonllm
Version: 0.0.1
Summary: Turn silly json into intelligent embeddings
Home-page: https://github.com/Florents-Tselai/jsonllm
Author: Florents Tselai
License: Apache License, Version 2.0
Project-URL: Issues, https://github.com/Florents-Tselai/jsonllm/issues
Project-URL: CI, https://github.com/Florents-Tselai/jsonllm/actions
Project-URL: Changelog, https://github.com/Florents-Tselai/jsonllm/releases
Requires-Python: >=3.7
License-File: LICENSE
Requires-Dist: click
Requires-Dist: setuptools
Requires-Dist: pip
Provides-Extra: test
Requires-Dist: pytest ; extra == 'test'
Requires-Dist: pytest-cov ; extra == 'test'
Requires-Dist: black ; extra == 'test'
Requires-Dist: ruff ; extra == 'test'
Requires-Dist: click ; extra == 'test'
